led_ctl-1.0.0.dist-info/licenses/LICENSE
sch/__init__.py
sch/led_control/__init__.py
sch/led_control/led.py
led_ctl-1.0.0.dist-info/METADATA
led_ctl-1.0.0.dist-info/WHEEL
led_ctl-1.0.0.dist-info/entry_points.txt
led_ctl-1.0.0.dist-info/top_level.txt
led_ctl-1.0.0.dist-info/RECORD
