Metadata-Version: 2.4
Name: led_ctl
Version: 1.0.0
Summary: Control LEDs with Python
Author-email: schlibra <schlibra@163.com>
Project-URL: Homepage, https://github.com/schlibra/led_ctl
Project-URL: Repository, https://github.com/schlibra/led_ctl
Project-URL: Issue, https://github.com/schlibra/led_ctl/issues
Keywords: linux,led,web,control
Requires-Python: >=3.9
License-File: LICENSE
Dynamic: license-file
